{"chunk_definitions":[{"row":139,"row_count":1,"visible":true,"expansion_state":0,"options":{"engine":"r","label":"setup","include":false},"document_id":"0155D7BA","chunk_id":"csetup_chunk","chunk_label":"setup"},{"row":190,"row_count":1,"visible":true,"expansion_state":0,"options":{"engine":"r","label":"datasets"},"document_id":"0155D7BA","chunk_id":"c49xa9juv6gkc","chunk_label":"datasets"},{"row":464,"row_count":1,"visible":true,"expansion_state":0,"options":{"engine":"r","label":"plotly-conflict-scatterplot"},"document_id":"0155D7BA","chunk_id":"cibs5or6zy4uc","chunk_label":"plotly-conflict-scatterplot"},{"row":847,"row_count":1,"visible":true,"expansion_state":0,"options":{"engine":"r","label":"plotly-tsp-reached-groups"},"document_id":"0155D7BA","chunk_id":"cxd769h4ta2bh","chunk_label":"plotly-tsp-reached-groups"},{"row":886,"row_count":1,"visible":true,"expansion_state":0,"options":{"engine":"r","label":"table-reached-group"},"document_id":"0155D7BA","chunk_id":"cch285nynl1pk","chunk_label":"table-reached-group"}],"doc_write_time":1664962989,"working_dir":null,"default_chunk_options":{"echo":false,"fig.width":9.0,"message":false,"warning":false}}